pylate/__init__.py
pylate/__version__.py
pylate/py.typed
pylate/evaluation/__init__.py
pylate/evaluation/beir.py
pylate/evaluation/colbert_distillation.py
pylate/evaluation/colbert_triplet.py
pylate/evaluation/custom_dataset.py
pylate/evaluation/nano_beir_evaluator.py
pylate/evaluation/pylate_information_retrieval_evaluator.py
pylate/hf_hub/__init__.py
pylate/hf_hub/model_card.py
pylate/hf_hub/model_card_template.md
pylate/indexes/__init__.py
pylate/indexes/base.py
pylate/indexes/fast_plaid.py
pylate/indexes/plaid.py
pylate/indexes/stanford_plaid.py
pylate/indexes/voyager.py
pylate/indexes/stanford_nlp/__init__.py
pylate/indexes/stanford_nlp/index_updater.py
pylate/indexes/stanford_nlp/indexer.py
pylate/indexes/stanford_nlp/parameters.py
pylate/indexes/stanford_nlp/searcher.py
pylate/indexes/stanford_nlp/data/__init__.py
pylate/indexes/stanford_nlp/data/collection.py
pylate/indexes/stanford_nlp/indexing/collection_indexer.py
pylate/indexes/stanford_nlp/indexing/index_manager.py
pylate/indexes/stanford_nlp/indexing/index_saver.py
pylate/indexes/stanford_nlp/indexing/loaders.py
pylate/indexes/stanford_nlp/indexing/utils.py
pylate/indexes/stanford_nlp/indexing/codecs/decompress_residuals.cpp
pylate/indexes/stanford_nlp/indexing/codecs/decompress_residuals.cu
pylate/indexes/stanford_nlp/indexing/codecs/packbits.cpp
pylate/indexes/stanford_nlp/indexing/codecs/packbits.cu
pylate/indexes/stanford_nlp/indexing/codecs/residual.py
pylate/indexes/stanford_nlp/indexing/codecs/residual_embeddings.py
pylate/indexes/stanford_nlp/indexing/codecs/residual_embeddings_strided.py
pylate/indexes/stanford_nlp/infra/__init__.py
pylate/indexes/stanford_nlp/infra/launcher.py
pylate/indexes/stanford_nlp/infra/run.py
pylate/indexes/stanford_nlp/infra/config/__init__.py
pylate/indexes/stanford_nlp/infra/config/base_config.py
pylate/indexes/stanford_nlp/infra/config/config.py
pylate/indexes/stanford_nlp/infra/config/core_config.py
pylate/indexes/stanford_nlp/infra/config/settings.py
pylate-1.3.4.dist-info/licenses/LICENSE
pylate-1.3.4.dist-info/METADATA
pylate-1.3.4.dist-info/WHEEL
pylate-1.3.4.dist-info/top_level.txt
pylate-1.3.4.dist-info/RECORD
