Metadata-Version: 2.4
Name: pylate
Version: 1.3.4
Summary: A library for training and retrieval with ColBERT.
Author: LightOn
License-Expression: MIT
Project-URL: Homepage, https://github.com/lightonai/pylate.git
Project-URL: Documentation, https://lightonai.github.io/pylate/
Classifier: Programming Language :: Python :: 3
Classifier: Operating System :: OS Independent
Requires-Python: >=3.9
License-File: LICENSE
Requires-Dist: sentence-transformers==5.1.1
Requires-Dist: datasets>=2.20.0
Requires-Dist: accelerate>=0.31.0
Requires-Dist: voyager>=2.0.9
Requires-Dist: sqlitedict>=2.1.0
Requires-Dist: pandas>=2.2.1
Requires-Dist: transformers<=4.56.2,>=4.41.0
Requires-Dist: ujson==5.10.0
Requires-Dist: ninja==1.11.1.4
Requires-Dist: fastkmeans==0.5.0
Requires-Dist: fast-plaid<=1.2.4.280,>=1.2.4.260
Provides-Extra: dev
Requires-Dist: ruff>=0.4.9; extra == "dev"
Requires-Dist: pytest-cov>=5.0.0; extra == "dev"
Requires-Dist: pytest-xdist>=3.6.0; extra == "dev"
Requires-Dist: pytest-rerunfailures>=15.0.0; extra == "dev"
Requires-Dist: pytest>=8.2.1; extra == "dev"
Requires-Dist: pandas>=2.2.1; extra == "dev"
Requires-Dist: mkdocs-material==9.5.32; extra == "dev"
Requires-Dist: mkdocs-awesome-pages-plugin==2.9.3; extra == "dev"
Requires-Dist: mkdocs-jupyter==0.24.8; extra == "dev"
Requires-Dist: mkdocs_charts_plugin==0.0.10; extra == "dev"
Requires-Dist: numpydoc==1.8.0; extra == "dev"
Requires-Dist: einops>=0.8.1; extra == "dev"
Requires-Dist: pre-commit>=4.1.0; extra == "dev"
Requires-Dist: ranx>=0.3.16; extra == "dev"
Requires-Dist: beir>=2.0.0; extra == "dev"
Requires-Dist: fastapi>=0.114.1; extra == "dev"
Requires-Dist: uvicorn>=0.30.6; extra == "dev"
Requires-Dist: batched>=0.1.2; extra == "dev"
Provides-Extra: eval
Requires-Dist: ranx>=0.3.16; extra == "eval"
Requires-Dist: beir>=2.0.0; extra == "eval"
Provides-Extra: api
Requires-Dist: fastapi>=0.114.1; extra == "api"
Requires-Dist: uvicorn>=0.30.6; extra == "api"
Requires-Dist: batched>=0.1.2; extra == "api"
Dynamic: license-file
